{"p":163,"l":2,"n":14,"spine":[true,true,false,false,false,false,false,false,false,false,false,false,false,false],"dist":[0,0,3,1,3,2,2,3,3,2,2,3,1,3],"maxDist":3,"edges":[[0,1],[1,3],[1,12],[2,7],[2,10],[2,13],[3,6],[3,10],[4,5],[4,11],[5,12],[5,13],[6,7],[6,9],[7,8],[8,9],[8,13],[9,12],[10,11]],"spineType":"line","spineOrder":[0,1],"hist":[[0,2],[1,2],[2,4],[3,6]],"pos":[[0,-26],[0,26],[-165.6,7.7],[-53.5,8.8],[166.3,9.6],[-104.8,25.4],[113.3,-6.3],[162.7,-5.6],[-163,59.2],[107.5,58.9],[-97.9,44.7],[166.7,44.5],[53.7,42],[-180.8,41]],"bbox":[-180.7577098003966,-26,166.69713792938913,59.21545474829597]}