{"p":4133,"l":7,"n":345,"spine":[true,true,true,true,true,true,true,true,true,true,true,true,true,true,true,true,true,true,true,true,true,true,true,true,true,true,true,true,true,true,true,true,true,true,true,true,true,true,true,false,false,false,false,false,false,false,false,false,false,false,false,false,false,false,false,false,false,false,false,false,false,false,false,false,false,false,false,false,false,false,false,false,false,false,false,false,false,false,false,false,false,false,false,false,false,false,false,false,false,false,false,false,false,false,false,false,false,false,false,false,false,false,false,false,false,false,false,false,false,false,false,false,false,false,false,false,false,false,false,false,false,false,false,false,false,false,false,false,false,false,false,false,false,false,false,false,false,false,false,false,false,false,false,false,false,false,false,false,false,false,false,false,false,false,false,false,false,false,false,false,false,false,false,false,false,false,false,false,false,false,false,false,false,false,false,false,false,false,false,false,false,false,false,false,false,false,false,false,false,false,false,false,false,false,false,false,false,false,false,false,false,false,false,false,false,false,false,false,false,false,false,false,false,false,false,false,false,false,false,false,false,false,false,false,false,false,false,false,false,false,false,false,false,false,false,false,false,false,false,false,false,false,false,false,false,false,false,false,false,false,false,false,false,false,false,false,false,false,false,false,false,false,false,false,false,false,false,false,false,false,false,false,false,false,false,false,false,false,false,false,false,false,false,false,false,false,false,false,false,false,false,false,false,false,false,false,false,false,false,false,false,false,false,false,false,false,false,false,false,false,false,false,false,false,false,false,false,false,false,false,false,false,false,false,false,false,false,false,false,false,false,false,false,false,false,false,false,false,false,false,false,false,false,false,false],"dist":[0,0,0,0,0,0,0,0,0,0,0,0,0,0,0,0,0,0,0,0,0,0,0,0,0,0,0,0,0,0,0,0,0,0,0,0,0,0,0,2,2,2,1,2,2,1,1,2,2,2,1,2,2,1,2,2,2,2,1,1,2,2,1,2,2,2,2,1,1,1,1,1,1,1,3,2,1,2,1,2,1,2,1,2,2,1,2,1,3,2,1,1,1,1,1,1,1,2,1,2,1,2,1,2,1,1,1,1,1,2,1,1,1,1,2,2,1,1,1,2,2,2,1,1,2,1,1,2,1,1,1,1,1,1,1,2,1,2,2,2,1,2,1,2,1,2,2,2,2,2,1,2,2,1,2,1,2,1,2,1,2,1,2,1,2,2,1,1,1,1,1,1,1,2,2,1,1,2,1,1,1,2,2,2,2,2,1,1,1,1,1,1,1,1,1,2,1,1,1,2,2,2,1,2,2,1,1,1,1,2,1,1,1,2,1,1,1,2,1,2,2,1,1,2,1,1,2,2,2,2,1,2,2,2,2,1,2,2,1,1,1,2,1,2,2,2,1,2,1,2,1,2,2,1,2,2,1,2,2,2,1,2,1,1,2,1,1,1,1,2,2,1,2,2,2,2,2,1,1,1,2,2,1,2,1,1,1,2,2,1,2,1,2,2,1,1,2,1,1,1,2,1,2,2,2,1,1,2,2,1,1,2,1,2,2,2,1,2,1,1,2,2,1,2,2,2,2,1,1,1,2,2,1,2,2,2,1,2,1,2,2,2,2,1,1],"maxDist":3,"edges":[[0,11],[0,14],[1,5],[1,19],[1,71],[1,73],[1,92],[1,105],[1,155],[1,262],[2,27],[2,29],[2,104],[2,118],[2,190],[2,285],[2,336],[2,344],[3,11],[3,30],[3,122],[3,132],[3,218],[3,279],[3,294],[3,332],[4,16],[4,23],[4,123],[4,212],[4,235],[4,253],[5,21],[5,53],[5,98],[5,128],[5,240],[5,268],[5,295],[6,14],[6,32],[6,122],[6,163],[6,193],[6,239],[6,282],[6,294],[7,15],[7,30],[7,53],[7,98],[7,131],[7,196],[7,267],[7,297],[8,10],[8,19],[8,94],[8,198],[8,206],[8,208],[8,278],[8,299],[9,33],[9,34],[9,108],[9,118],[9,150],[9,215],[9,289],[9,344],[10,53],[10,72],[10,78],[10,98],[10,285],[10,336],[11,116],[11,186],[11,214],[11,246],[11,256],[11,260],[12,17],[12,26],[12,42],[12,248],[12,263],[12,310],[12,319],[12,338],[13,22],[13,27],[13,93],[13,126],[13,178],[13,263],[13,310],[13,329],[14,46],[14,107],[14,169],[14,180],[14,202],[14,266],[15,38],[15,45],[15,59],[15,67],[15,130],[15,305],[15,309],[16,28],[16,46],[16,110],[16,133],[16,168],[16,202],[16,222],[17,31],[17,62],[17,87],[17,134],[17,144],[17,171],[17,179],[18,34],[18,38],[18,69],[18,71],[18,73],[18,132],[18,167],[18,332],[19,27],[19,102],[19,142],[19,163],[19,193],[20,22],[20,24],[20,76],[20,91],[20,113],[20,117],[20,170],[20,298],[21,35],[21,96],[21,116],[21,125],[21,192],[21,246],[21,343],[22,30],[22,62],[22,134],[22,150],[22,289],[23,37],[23,176],[23,180],[23,186],[23,238],[23,260],[23,266],[24,32],[24,166],[24,188],[24,224],[24,242],[24,284],[24,328],[25,31],[25,36],[25,82],[25,90],[25,95],[25,159],[25,210],[25,318],[26,35],[26,68],[26,85],[26,157],[26,191],[26,286],[26,312],[27,45],[27,130],[27,301],[27,316],[28,29],[28,129],[28,166],[28,172],[28,224],[28,265],[28,291],[29,58],[29,87],[29,171],[29,189],[29,221],[29,230],[30,100],[30,111],[30,161],[30,175],[31,153],[31,197],[31,211],[31,322],[32,70],[32,104],[32,190],[32,191],[32,225],[32,286],[33,37],[33,128],[33,205],[33,263],[33,268],[33,271],[33,310],[34,140],[34,187],[34,207],[34,216],[35,80],[35,129],[35,240],[35,291],[35,295],[35,306],[36,106],[36,112],[36,248],[36,277],[36,327],[36,338],[37,50],[37,80],[37,166],[37,194],[37,224],[37,306],[38,87],[38,104],[38,136],[38,171],[38,190],[38,250],[39,55],[39,113],[39,142],[39,155],[39,165],[39,312],[39,325],[39,330],[40,47],[40,66],[40,179],[40,224],[40,247],[40,275],[40,291],[40,298],[41,72],[41,89],[41,95],[41,138],[41,178],[41,180],[41,267],[41,324],[42,52],[42,56],[42,75],[42,96],[42,152],[42,173],[42,330],[43,74],[43,79],[43,165],[43,202],[43,232],[43,241],[43,249],[43,282],[44,102],[44,147],[44,157],[44,170],[44,183],[44,245],[44,262],[44,272],[45,46],[45,89],[45,126],[45,180],[45,303],[45,313],[46,195],[46,199],[46,242],[46,269],[46,334],[47,160],[47,185],[47,193],[47,204],[47,228],[47,273],[47,307],[48,114],[48,149],[48,151],[48,209],[48,220],[48,236],[48,279],[48,294],[49,74],[49,87],[49,117],[49,135],[49,158],[49,168],[49,245],[49,273],[50,110],[50,126],[50,194],[50,207],[50,225],[50,258],[50,309],[51,72],[51,126],[51,158],[51,164],[51,181],[51,191],[51,230],[51,253],[52,55],[52,62],[52,74],[52,201],[52,224],[52,276],[52,326],[53,64],[53,99],[53,133],[53,195],[53,261],[54,111],[54,175],[54,205],[54,206],[54,253],[54,277],[54,319],[54,320],[55,105],[55,180],[55,204],[55,275],[55,277],[55,325],[56,114],[56,121],[56,147],[56,181],[56,235],[56,259],[56,283],[57,70],[57,72],[57,80],[57,81],[57,230],[57,259],[57,336],[57,337],[58,69],[58,203],[58,221],[58,242],[58,276],[58,279],[58,308],[59,140],[59,155],[59,162],[59,167],[59,219],[59,231],[59,328],[60,159],[60,173],[60,178],[60,199],[60,280],[60,281],[60,320],[60,333],[61,63],[61,75],[61,114],[61,215],[61,240],[61,250],[61,304],[61,319],[62,125],[62,185],[62,223],[62,251],[62,293],[63,146],[63,157],[63,229],[63,236],[63,272],[63,278],[63,302],[64,86],[64,153],[64,214],[64,228],[64,292],[64,306],[64,323],[65,118],[65,127],[65,175],[65,200],[65,210],[65,244],[65,267],[65,307],[66,102],[66,120],[66,243],[66,271],[66,285],[66,326],[67,111],[67,142],[67,177],[67,194],[67,197],[67,226],[67,336],[68,92],[68,196],[68,203],[68,210],[68,244],[68,293],[68,330],[69,102],[69,172],[69,185],[69,290],[69,298],[69,305],[70,115],[70,116],[70,165],[70,194],[70,248],[70,328],[71,76],[71,82],[71,156],[71,211],[71,248],[71,329],[72,110],[72,116],[72,172],[72,302],[73,90],[73,139],[73,153],[73,178],[73,298],[73,338],[74,88],[74,162],[74,228],[74,333],[75,108],[75,124],[75,136],[75,204],[75,295],[75,337],[76,150],[76,167],[76,222],[76,227],[76,253],[76,293],[77,154],[77,175],[77,222],[77,254],[77,258],[77,265],[77,281],[77,283],[78,158],[78,162],[78,168],[78,213],[78,246],[78,265],[78,335],[79,94],[79,97],[79,108],[79,119],[79,234],[79,274],[79,340],[80,106],[80,145],[80,152],[80,242],[80,325],[81,89],[81,115],[81,183],[81,287],[81,294],[81,297],[81,309],[82,90],[82,96],[82,129],[82,293],[82,310],[82,315],[83,231],[83,244],[83,260],[83,278],[83,288],[83,305],[83,338],[84,117],[84,129],[84,177],[84,227],[84,258],[84,287],[84,294],[84,315],[85,101],[85,105],[85,131],[85,182],[85,183],[85,300],[85,318],[86,108],[86,148],[86,216],[86,221],[86,308],[86,325],[87,119],[87,175],[87,249],[87,337],[88,143],[88,164],[88,201],[88,302],[88,311],[88,334],[89,235],[89,240],[89,244],[89,289],[89,325],[90,138],[90,182],[90,263],[90,291],[90,343],[91,107],[91,117],[91,164],[91,203],[91,215],[91,247],[91,317],[92,132],[92,263],[92,265],[92,272],[92,283],[92,333],[93,125],[93,130],[93,158],[93,185],[93,194],[93,203],[93,216],[94,112],[94,188],[94,192],[94,197],[94,310],[94,317],[95,113],[95,135],[95,156],[95,159],[95,162],[95,320],[96,123],[96,220],[96,261],[96,303],[96,343],[97,106],[97,111],[97,146],[97,160],[97,204],[97,287],[97,318],[98,141],[98,145],[98,181],[98,222],[98,287],[99,102],[99,146],[99,198],[99,216],[99,226],[99,247],[99,250],[100,135],[100,146],[100,168],[100,173],[100,290],[100,309],[100,324],[101,148],[101,209],[101,224],[101,231],[101,244],[101,274],[101,321],[102,138],[102,302],[102,309],[103,144],[103,152],[103,170],[103,229],[103,235],[103,238],[103,271],[103,334],[104,176],[104,179],[104,198],[104,257],[104,288],[105,119],[105,172],[105,310],[105,311],[105,332],[106,112],[106,154],[106,168],[106,299],[106,303],[107,136],[107,140],[107,169],[107,196],[107,281],[107,288],[108,117],[108,132],[108,267],[108,333],[109,139],[109,160],[109,214],[109,234],[109,252],[109,285],[109,295],[109,339],[110,111],[110,112],[110,164],[110,184],[110,239],[111,154],[111,249],[111,275],[112,146],[112,290],[112,306],[112,339],[113,160],[113,170],[113,232],[113,304],[113,316],[114,135],[114,238],[114,297],[114,314],[114,318],[115,156],[115,164],[115,235],[115,236],[115,281],[115,283],[116,216],[116,271],[116,293],[116,324],[117,169],[117,300],[117,326],[118,156],[118,181],[118,237],[118,281],[118,328],[119,121],[119,197],[119,270],[119,273],[119,288],[120,137],[120,147],[120,210],[120,224],[120,278],[120,290],[120,344],[121,124],[121,195],[121,199],[121,212],[121,319],[121,325],[122,174],[122,178],[122,226],[122,247],[122,307],[122,338],[123,158],[123,173],[123,298],[123,312],[123,316],[123,322],[124,176],[124,210],[124,267],[124,275],[124,276],[124,307],[125,174],[125,228],[125,262],[125,267],[125,299],[126,149],[126,187],[126,192],[126,300],[127,163],[127,168],[127,210],[127,222],[127,241],[127,251],[127,296],[128,151],[128,157],[128,245],[128,262],[128,329],[128,337],[129,149],[129,227],[129,297],[129,311],[130,202],[130,264],[130,266],[130,321],[130,339],[131,148],[131,169],[131,196],[131,220],[131,233],[131,239],[132,208],[132,229],[132,242],[132,332],[133,153],[133,184],[133,189],[133,250],[133,270],[133,298],[134,149],[134,177],[134,182],[134,192],[134,201],[134,217],[135,188],[135,208],[135,227],[135,272],[136,181],[136,222],[136,264],[136,287],[136,337],[137,144],[137,148],[137,245],[137,256],[137,262],[137,324],[138,216],[138,228],[138,234],[138,247],[138,292],[139,156],[139,159],[139,189],[139,264],[139,273],[139,344],[140,143],[140,194],[140,207],[140,235],[140,313],[141,174],[141,199],[141,261],[141,264],[141,316],[141,342],[141,343],[142,162],[142,167],[142,243],[142,287],[142,315],[143,145],[143,172],[143,192],[143,228],[143,236],[143,315],[144,179],[144,190],[144,218],[144,227],[144,311],[145,211],[145,256],[145,281],[145,288],[145,308],[146,210],[146,340],[146,341],[147,255],[147,272],[147,306],[147,308],[147,321],[148,162],[148,191],[148,238],[148,320],[149,167],[149,236],[149,240],[149,260],[150,282],[150,289],[150,321],[150,323],[151,230],[151,234],[151,252],[151,301],[151,315],[151,340],[152,172],[152,190],[152,219],[152,235],[152,254],[153,177],[153,208],[153,212],[153,220],[154,167],[154,214],[154,237],[154,290],[154,337],[155,192],[155,258],[155,268],[155,331],[156,230],[156,252],[156,313],[157,253],[157,279],[157,317],[157,327],[158,189],[158,195],[158,286],[159,170],[159,275],[159,302],[159,335],[160,178],[160,251],[160,254],[160,341],[161,171],[161,173],[161,209],[161,233],[161,259],[161,270],[161,300],[162,204],[162,316],[163,193],[163,203],[163,214],[163,236],[163,293],[164,165],[164,171],[164,275],[165,180],[165,268],[165,281],[165,331],[166,201],[166,217],[166,227],[166,237],[166,244],[167,221],[167,265],[168,194],[168,282],[169,207],[169,250],[169,292],[169,323],[170,301],[170,337],[170,341],[171,283],[171,304],[171,324],[172,248],[172,270],[173,271],[173,278],[173,327],[174,202],[174,269],[174,278],[174,288],[174,328],[175,199],[175,203],[175,258],[176,178],[176,203],[176,232],[176,251],[176,280],[177,218],[177,223],[177,284],[177,301],[178,268],[179,232],[179,279],[179,331],[179,333],[180,240],[180,310],[181,202],[181,206],[181,241],[182,193],[182,246],[182,255],[182,298],[182,314],[183,219],[183,301],[183,319],[183,330],[184,193],[184,209],[184,217],[184,219],[184,220],[184,318],[185,186],[185,291],[185,295],[185,307],[186,189],[186,191],[186,231],[186,255],[186,274],[187,210],[187,246],[187,287],[187,296],[187,308],[187,315],[188,225],[188,269],[188,305],[188,328],[188,344],[189,200],[189,213],[189,234],[190,208],[190,238],[190,323],[191,208],[191,219],[191,303],[192,269],[192,297],[193,256],[193,300],[194,233],[195,220],[195,250],[195,278],[195,344],[196,241],[196,258],[196,280],[196,282],[197,253],[197,255],[197,256],[197,314],[198,208],[198,211],[198,275],[198,286],[198,332],[199,200],[199,213],[199,251],[200,204],[200,232],[200,263],[200,282],[200,332],[201,272],[201,314],[201,317],[201,319],[202,259],[202,284],[203,300],[204,206],[204,312],[205,232],[205,243],[205,246],[205,258],[205,274],[205,323],[206,231],[206,237],[206,269],[206,277],[207,212],[207,228],[207,264],[207,305],[208,287],[209,229],[209,297],[209,318],[209,344],[211,222],[211,223],[211,235],[211,241],[212,232],[212,257],[212,273],[212,321],[213,225],[213,226],[213,285],[213,304],[213,306],[214,277],[214,322],[214,331],[215,297],[215,308],[215,311],[215,332],[215,340],[216,219],[216,318],[217,218],[217,238],[217,251],[217,259],[217,341],[218,221],[218,277],[218,307],[218,312],[219,304],[219,324],[220,326],[220,334],[221,284],[221,300],[221,314],[222,230],[223,242],[223,247],[223,279],[223,309],[223,316],[224,251],[225,245],[225,246],[225,273],[225,338],[226,267],[226,273],[226,321],[226,330],[227,236],[227,243],[228,265],[229,230],[229,239],[229,259],[229,310],[230,260],[231,248],[231,323],[232,257],[233,247],[233,262],[233,270],[233,271],[233,326],[234,268],[234,307],[234,316],[236,341],[237,243],[237,318],[237,325],[237,331],[238,300],[238,329],[239,282],[239,285],[239,289],[239,334],[240,252],[240,314],[241,307],[241,317],[241,343],[242,284],[242,313],[243,317],[243,336],[244,280],[244,342],[245,266],[245,292],[245,334],[246,249],[247,291],[248,294],[248,314],[249,277],[249,296],[249,331],[249,335],[250,304],[250,313],[251,279],[252,256],[252,303],[252,336],[252,341],[253,301],[253,343],[254,260],[254,293],[254,322],[254,325],[254,342],[255,257],[255,270],[255,274],[255,341],[256,290],[256,327],[257,265],[257,296],[257,306],[257,319],[258,317],[259,261],[259,320],[260,286],[260,342],[261,269],[261,274],[261,301],[261,313],[262,305],[263,266],[263,299],[264,276],[264,284],[264,326],[265,338],[266,272],[266,295],[266,335],[267,291],[268,304],[268,312],[269,294],[269,323],[270,290],[270,292],[271,288],[271,342],[272,327],[273,292],[274,336],[274,342],[275,328],[276,293],[276,295],[276,322],[276,338],[277,312],[278,327],[279,327],[280,286],[280,302],[280,308],[280,331],[281,315],[282,336],[283,322],[283,323],[283,340],[284,306],[284,332],[285,309],[285,342],[286,296],[286,339],[288,289],[289,298],[290,304],[291,333],[292,320],[292,344],[294,329],[295,321],[296,305],[296,330],[296,337],[297,335],[299,322],[299,326],[299,328],[299,340],[301,302],[302,305],[303,311],[303,339],[309,322],[311,320],[311,333],[312,326],[313,314],[313,317],[315,335],[316,330],[319,343],[320,329],[321,335],[324,327],[324,334],[329,335],[329,341],[333,339],[334,340],[339,343],[340,342]],"spineType":"generic","spineOrder":[0,1,2,3,4,5,6,7,8,9,10,11,12,13,14,15,16,17,18,19,20,21,22,23,24,25,26,27,28,29,30,31,32,33,34,35,36,37,38],"hist":[[0,39],[1,156],[2,148],[3,2]],"pos":[[322.8,0],[318.6,51.8],[306.2,102.2],[285.8,150],[258,193.9],[223.6,232.8],[183.4,265.6],[138.4,291.6],[89.8,310],[38.9,320.4],[-13,322.5],[-64.6,316.2],[-114.5,301.8],[-161.4,279.5],[-204.1,250],[-241.6,214],[-272.8,172.5],[-296.9,126.5],[-313.4,77.2],[-321.7,26],[-321.7,-26],[-313.4,-77.2],[-296.9,-126.5],[-272.8,-172.5],[-241.6,-214],[-204.1,-250],[-161.4,-279.5],[-114.5,-301.8],[-64.6,-316.2],[-13,-322.5],[38.9,-320.4],[89.8,-310],[138.4,-291.6],[183.4,-265.6],[223.6,-232.8],[258,-193.9],[285.8,-150],[306.2,-102.2],[318.6,-51.8],[423.3,19.8],[-419.8,55.2],[247,345.1],[-20.5,368.7],[156.6,405.1],[418,73.2],[-195,310.8],[-134.9,344.4],[346.7,243.8],[425.1,133.8],[-375,200.6],[302.9,-202.2],[342.1,270.3],[73.5,419.1],[317.5,185.4],[154.7,394.5],[428.3,-12.9],[380.6,190.6],[417,83.7],[-114,-345.2],[-229.2,283.1],[-134,404.8],[352.8,255.3],[-278.9,241.5],[163.8,392],[409.7,110.4],[421.5,-53.9],[422.2,46.7],[-255,260],[-263.9,-250.7],[-319.1,177.6],[65.7,-358.1],[361.2,-40.9],[97.7,355.9],[363.4,-1.8],[447.7,190],[297.9,310.9],[-357.1,77.9],[-405.2,123.7],[-113.5,347],[317.4,286.9],[230.3,-287.1],[394.5,161.7],[-300.8,-206.1],[-75.8,420.2],[335.5,260.2],[-233.8,-278.7],[171.7,390.9],[-303.9,201.9],[424.2,238.1],[351.2,262.7],[-274.8,-238.8],[-364.6,41.4],[364.6,31.4],[-79.7,358.5],[193,308.4],[-251.6,-264.5],[-365,20.2],[-166.5,-389.6],[294.4,218.2],[369.5,211.2],[-60.1,-358.8],[-333,-261.4],[-340.1,137.8],[283.2,322.3],[363.8,16.8],[355.5,83.6],[265,-249],[-173.3,322.8],[150.3,336.8],[406.4,125.9],[-237.6,278.2],[10.6,-363.2],[307,-195.4],[-364.6,-3.9],[184.5,383.3],[231.5,357.7],[31.3,363.1],[-366.2,-37.4],[361.9,58.5],[414.8,95.3],[400.4,136.6],[407.9,119.8],[357.8,77.3],[341.5,127.3],[44.1,425.5],[-361.5,-48.4],[-150.2,331.8],[386.6,174.1],[268.4,246.9],[-168.6,-322.2],[-286.6,231.5],[244.5,272.6],[346.3,114.2],[-289.3,220.7],[-324.5,167],[90,414.6],[335.7,-146],[383.8,185.3],[-395.7,154.9],[425.9,6.2],[171.8,-320.4],[396.1,152],[-359.1,-64.3],[-399.8,-139.7],[-341,128.4],[345.4,250],[-211,-367.2],[406.2,-142.1],[356.9,231.1],[272.3,326.3],[69,360.7],[375,198.8],[424.5,-2.2],[6.2,-363.7],[-60.2,419.6],[344.8,124.2],[423.6,-41.3],[-198.5,-304.3],[422.5,39.3],[-213.6,-294.2],[-326.4,271.9],[80,-354.7],[-129.1,403.8],[280.4,237.3],[-277.2,325.9],[325.5,273.2],[-328.3,-156.8],[-364.4,-14.7],[-321.7,172.5],[-208.1,301.2],[-354.1,-85.1],[-352.8,89.2],[-106.2,-347.6],[339.1,252],[423.3,-25.9],[146.4,-333.8],[-350.6,-98.2],[419,62.9],[-202.5,308.4],[-360.6,52.3],[-242.8,272.9],[426.4,38.4],[296.6,303.1],[-97.7,414.7],[236.8,351],[196.1,377],[-13.7,363.9],[228.2,-282.8],[-309.4,-191],[-45.2,-360.7],[351.5,95.4],[-162.2,-325.3],[-348,-111.6],[227.3,295.1],[363.5,-16.7],[377.8,227.7],[185.1,315.9],[72.7,-356.3],[164.5,326.8],[-160.3,395.5],[310.8,295.9],[-299.7,304],[-270.2,245.6],[359.5,239.9],[243.8,347.9],[128.2,-343.3],[141.6,350],[274.7,-238.1],[85.8,354.7],[331.2,266.1],[-176,-319.2],[140.9,-337],[313.8,191.1],[377.7,194],[-40,367.4],[21.4,369.6],[317,-179.4],[321.2,276.9],[335.2,145.7],[-261.4,335.9],[179.5,376],[20.9,-363.1],[-348.5,103.5],[364.4,216.2],[-285.4,-225.3],[245.5,-270.2],[428.2,67],[-398,145.8],[-418.6,-63.6],[405.4,139.5],[94.3,-353.6],[14.5,429.1],[385.8,189],[319.8,280.9],[235.8,354.6],[282.7,242.1],[300.4,319.2],[412.5,101.9],[-242.3,-270.7],[180.9,325.9],[237.3,281.9],[307.1,294],[-256.9,-258.1],[389.7,169.5],[-382.6,-181.7],[313.3,288.9],[-92.3,352.1],[404,129.7],[-65.6,358.8],[-103.6,412.8],[364.1,53.8],[285.5,317.9],[353.4,238.5],[219.3,289.9],[-189.8,379.6],[-9.9,424.5],[-121.1,346.9],[415,-90.1],[400.9,144],[-316.2,283.4],[-164.8,324.7],[290.3,311.3],[328.4,163.3],[-103.7,350.5],[-243.5,347.8],[-40.8,-361.4],[-294.9,217.1],[133.8,341],[208.7,299.4],[254,340],[-333.2,262.7],[295.7,-224.9],[421.2,-63.1],[367.6,257.6],[303.6,300.5],[188.5,380.4],[83.3,417.7],[341.4,-131.7],[59.1,368.4],[313.2,185.7],[106.7,409.5],[384.3,180.4],[107.7,355.6],[422.4,54.2],[-226.3,-285.3],[339.6,150.5],[-130.2,-339.5],[263.7,333.3],[418.1,154.2],[-55.3,360.9],[-154.9,395.8],[32.5,-363],[265.9,337.3],[240.2,364.6],[287.3,236.3],[172.9,323.4],[-356.6,229.7],[62,359.5],[-343.4,-121.8],[0.9,363.9],[171.1,387.5],[-218.9,-290.3],[97.2,412.9],[-122.1,405.8],[127.9,406.8],[-308.8,194],[349.4,-125.1],[391.4,222.6],[17.3,424.2],[-328,156.8],[-143.2,335.9],[371.6,207.3],[-83,-355],[-312.2,290.1],[177.1,387],[-415.9,-80],[-28.4,-362.5],[117.1,407.6],[-140.6,-335.9],[-180.3,317.6],[-205.4,373.8],[282.2,312.7],[197,-306.2],[362.2,227],[30.9,423.8],[269.2,-332.8],[104.2,421.1],[360.2,-66.9],[-192.6,-309.1],[-260.4,255.4],[-146.2,398.6],[348.2,259.8],[260,258.3],[391.9,165.4],[208.8,384.8],[-52.4,422.6],[321.2,180.4],[215.2,366.5],[-215.1,293.5],[-390.2,165],[-108.5,410.7],[-370.2,209.8],[333.3,273.3],[-320.5,-174.4],[302.9,205.3]],"bbox":[-419.8430528295457,-389.55426439035034,447.71502570610375,429.05297838357205]}