{"p":4297,"l":5,"n":358,"spine":[true,true,true,true,true,true,true,true,true,true,true,true,true,true,true,true,true,true,false,false,false,false,false,false,false,false,false,false,false,false,false,false,false,false,false,false,false,false,false,false,false,false,false,false,false,false,false,false,false,false,false,false,false,false,false,false,false,false,false,false,false,false,false,false,false,false,false,false,false,false,false,false,false,false,false,false,false,false,false,false,false,false,false,false,false,false,false,false,false,false,false,false,false,false,false,false,false,false,false,false,false,false,false,false,false,false,false,false,false,false,false,false,false,false,false,false,false,false,false,false,false,false,false,false,false,false,false,false,false,false,false,false,false,false,false,false,false,false,false,false,false,false,false,false,false,false,false,false,false,false,false,false,false,false,false,false,false,false,false,false,false,false,false,false,false,false,false,false,false,false,false,false,false,false,false,false,false,false,false,false,false,false,false,false,false,false,false,false,false,false,false,false,false,false,false,false,false,false,false,false,false,false,false,false,false,false,false,false,false,false,false,false,false,false,false,false,false,false,false,false,false,false,false,false,false,false,false,false,false,false,false,false,false,false,false,false,false,false,false,false,false,false,false,false,false,false,false,false,false,false,false,false,false,false,false,false,false,false,false,false,false,false,false,false,false,false,false,false,false,false,false,false,false,false,false,false,false,false,false,false,false,false,false,false,false,false,false,false,false,false,false,false,false,false,false,false,false,false,false,false,false,false,false,false,false,false,false,false,false,false,false,false,false,false,false,false,false,false,false,false,false,false,false,false,false,false,false,false,false,false,false,false,false,false,false,false,false,false,false,false,false,false,false,false,false,false,false,false,false,false,false,false,false,false,false,false,false,false],"dist":[0,0,0,0,0,0,0,0,0,0,0,0,0,0,0,0,0,0,2,2,3,1,1,1,2,1,2,1,2,1,3,1,1,2,3,2,3,2,1,2,2,2,1,1,3,2,2,2,1,3,1,1,1,3,2,2,2,2,1,2,2,2,2,1,2,2,1,2,2,1,2,2,2,3,1,2,3,2,3,2,3,2,2,2,3,2,2,1,2,2,2,2,2,1,1,2,1,2,1,2,1,2,1,3,2,3,2,1,3,1,1,1,2,1,1,2,1,2,2,2,2,2,2,1,2,3,2,3,3,1,3,2,2,2,2,3,3,2,2,3,2,1,2,2,1,2,2,3,2,3,2,1,1,2,1,2,3,1,3,2,3,1,2,2,3,1,3,2,3,2,2,2,2,2,1,3,2,1,3,2,3,2,2,3,2,1,2,3,1,2,1,1,2,1,2,2,2,2,2,3,2,2,2,2,1,3,3,1,2,2,2,2,1,1,2,3,2,2,2,1,1,2,2,1,2,1,1,2,2,1,3,2,2,2,3,1,2,2,2,3,3,1,2,2,2,2,2,2,1,3,1,2,2,3,1,3,2,3,2,3,2,1,2,2,1,2,3,1,2,2,2,1,1,1,2,3,2,2,3,2,2,2,1,2,1,1,3,2,2,2,2,1,2,1,2,2,2,3,1,2,3,1,2,2,3,2,2,2,2,1,2,2,2,2,1,1,1,2,1,1,2,2,3,2,2,2,2,2,3,1,1,1,2,2,2,1,1,3,3,2,2,1,2,2,2,2,2,2,1,2,2,2,2,2,2,2,3,2],"maxDist":3,"edges":[[0,38],[0,52],[0,114],[0,219],[0,272],[0,331],[1,69],[1,74],[1,96],[1,107],[1,185],[1,193],[2,27],[2,42],[2,87],[2,110],[2,113],[2,335],[3,66],[3,98],[3,116],[3,285],[4,48],[4,93],[4,100],[4,248],[4,261],[4,341],[5,32],[5,63],[5,204],[5,241],[5,316],[5,318],[6,51],[6,223],[6,284],[6,293],[6,298],[6,309],[7,165],[7,190],[7,254],[7,271],[7,315],[7,319],[8,43],[8,102],[8,188],[8,348],[9,21],[9,22],[9,152],[9,154],[9,220],[9,235],[10,109],[10,111],[10,177],[10,212],[10,229],[10,282],[11,94],[11,96],[11,161],[11,193],[11,226],[11,301],[12,51],[12,141],[12,213],[12,273],[12,298],[12,329],[13,25],[13,151],[13,207],[13,250],[13,264],[13,336],[14,110],[14,113],[14,191],[14,225],[14,291],[14,330],[15,23],[15,48],[15,100],[15,109],[15,174],[15,212],[16,50],[16,129],[16,144],[16,157],[16,267],[16,314],[17,29],[17,31],[17,58],[17,123],[17,267],[17,314],[18,26],[18,31],[18,33],[18,82],[18,158],[18,268],[19,23],[19,49],[19,94],[19,127],[19,252],[19,347],[20,28],[20,79],[20,127],[20,158],[20,168],[20,197],[21,38],[21,195],[21,271],[21,341],[21,345],[22,122],[22,133],[22,219],[22,248],[22,319],[23,40],[23,52],[23,347],[23,354],[24,60],[24,93],[24,199],[24,250],[24,288],[24,333],[25,142],[25,153],[25,155],[25,233],[25,336],[26,38],[26,80],[26,214],[26,232],[26,328],[27,42],[27,195],[27,281],[27,321],[27,345],[28,58],[28,99],[28,234],[28,240],[28,246],[29,37],[29,132],[29,309],[29,313],[29,346],[30,198],[30,230],[30,244],[30,278],[30,321],[30,338],[31,35],[31,60],[31,237],[31,284],[32,35],[32,241],[32,305],[32,315],[32,326],[33,88],[33,171],[33,223],[33,244],[33,273],[34,101],[34,117],[34,126],[34,147],[34,253],[34,286],[35,197],[35,240],[35,247],[35,270],[36,60],[36,125],[36,130],[36,149],[36,163],[36,166],[37,143],[37,150],[37,164],[37,182],[37,317],[38,45],[38,292],[38,310],[39,63],[39,145],[39,201],[39,238],[39,297],[39,322],[40,116],[40,141],[40,157],[40,301],[40,324],[41,82],[41,216],[41,224],[41,269],[41,316],[41,320],[42,117],[42,122],[42,133],[42,355],[43,57],[43,67],[43,123],[43,140],[43,287],[44,75],[44,106],[44,296],[44,306],[44,334],[45,81],[45,127],[45,147],[45,153],[45,294],[46,50],[46,59],[46,143],[46,175],[46,176],[46,342],[47,66],[47,124],[47,135],[47,178],[47,181],[47,182],[48,115],[48,209],[48,245],[48,262],[49,64],[49,217],[49,294],[49,343],[50,72],[50,95],[50,196],[50,229],[51,65],[51,182],[51,261],[51,319],[52,93],[52,256],[52,323],[52,331],[53,217],[53,256],[53,260],[53,295],[53,310],[53,357],[54,55],[54,143],[54,248],[54,266],[54,315],[54,357],[55,123],[55,300],[55,316],[55,322],[55,333],[56,64],[56,160],[56,199],[56,211],[56,220],[56,309],[57,107],[57,145],[57,160],[57,202],[57,226],[58,64],[58,71],[58,289],[58,348],[59,96],[59,148],[59,202],[59,270],[59,306],[60,111],[60,124],[60,283],[61,137],[61,161],[61,185],[61,257],[61,280],[61,340],[62,70],[62,76],[62,122],[62,170],[62,298],[62,301],[63,113],[63,204],[63,207],[63,232],[64,79],[64,131],[64,321],[65,168],[65,195],[65,224],[65,226],[65,325],[66,134],[66,200],[66,295],[66,357],[67,106],[67,113],[67,114],[67,120],[67,305],[68,158],[68,173],[68,248],[68,253],[68,318],[68,323],[69,75],[69,120],[69,137],[69,185],[69,327],[70,119],[70,131],[70,232],[70,254],[70,314],[71,128],[71,159],[71,171],[71,240],[71,318],[72,86],[72,92],[72,133],[72,141],[72,239],[73,125],[73,126],[73,150],[73,210],[73,239],[73,259],[74,201],[74,247],[74,284],[74,311],[74,326],[75,189],[75,238],[75,246],[75,271],[76,135],[76,156],[76,183],[76,199],[76,354],[77,107],[77,149],[77,152],[77,230],[77,231],[77,254],[78,88],[78,222],[78,256],[78,325],[78,333],[78,349],[79,114],[79,178],[79,213],[79,299],[80,89],[80,125],[80,139],[80,198],[80,297],[81,169],[81,239],[81,284],[81,320],[81,329],[82,150],[82,218],[82,259],[82,291],[83,169],[83,219],[83,255],[83,283],[83,306],[83,338],[84,105],[84,160],[84,166],[84,227],[84,259],[84,265],[85,101],[85,103],[85,144],[85,180],[85,236],[85,303],[86,111],[86,197],[86,214],[86,231],[86,317],[87,203],[87,213],[87,274],[87,299],[87,341],[88,120],[88,129],[88,277],[88,353],[89,128],[89,210],[89,212],[89,276],[89,278],[90,103],[90,110],[90,118],[90,126],[90,160],[90,293],[91,151],[91,205],[91,285],[91,300],[91,325],[92,113],[92,183],[92,186],[92,193],[92,261],[93,176],[93,221],[93,298],[94,137],[94,148],[94,161],[94,177],[95,180],[95,239],[95,278],[95,336],[95,339],[96,165],[96,221],[96,268],[97,100],[97,177],[97,199],[97,209],[97,300],[97,302],[98,146],[98,196],[98,217],[98,242],[98,318],[99,125],[99,151],[99,159],[99,189],[99,302],[100,155],[100,202],[100,340],[101,105],[101,111],[101,114],[101,289],[102,118],[102,236],[102,246],[102,268],[102,271],[103,247],[103,279],[103,326],[103,327],[104,117],[104,142],[104,167],[104,223],[104,275],[104,306],[105,135],[105,205],[105,251],[105,317],[106,116],[106,153],[106,249],[106,275],[107,112],[107,138],[107,309],[108,124],[108,142],[108,169],[108,187],[108,259],[108,308],[109,218],[109,251],[109,346],[109,355],[110,121],[110,204],[110,221],[111,140],[111,195],[112,158],[112,226],[112,241],[112,274],[112,304],[113,208],[114,126],[114,242],[115,118],[115,155],[115,162],[115,206],[115,336],[116,179],[116,316],[116,320],[117,151],[117,321],[117,334],[118,277],[118,349],[118,351],[119,150],[119,242],[119,256],[119,292],[119,318],[120,186],[120,265],[120,322],[121,217],[121,218],[121,272],[121,342],[121,348],[122,173],[122,269],[122,282],[123,334],[123,349],[123,352],[124,161],[124,189],[124,353],[125,203],[125,356],[126,143],[126,355],[127,180],[127,255],[127,292],[128,134],[128,209],[128,237],[128,300],[129,142],[129,177],[129,179],[129,308],[130,202],[130,236],[130,322],[130,340],[130,354],[131,220],[131,277],[131,282],[131,348],[132,138],[132,210],[132,241],[132,322],[132,350],[133,229],[133,275],[133,315],[134,139],[134,170],[134,250],[135,145],[135,164],[135,187],[136,178],[136,183],[136,228],[136,252],[136,263],[136,280],[137,180],[137,245],[137,287],[138,149],[138,225],[138,281],[138,304],[139,203],[139,246],[139,280],[140,154],[140,176],[140,224],[140,334],[141,228],[141,335],[141,350],[142,257],[142,286],[143,293],[143,329],[144,146],[144,242],[144,289],[144,305],[145,204],[145,240],[145,299],[146,174],[146,213],[146,226],[146,357],[147,160],[147,232],[147,233],[147,260],[148,231],[148,239],[148,263],[148,313],[149,239],[149,269],[149,297],[150,305],[150,330],[151,154],[151,312],[152,179],[152,207],[152,233],[152,324],[153,283],[153,313],[153,316],[154,192],[154,211],[154,222],[155,258],[155,275],[155,344],[156,164],[156,210],[156,228],[156,255],[156,352],[157,218],[157,320],[157,332],[157,349],[158,159],[158,297],[159,175],[159,291],[159,312],[160,162],[161,229],[161,296],[162,237],[162,268],[162,273],[162,344],[163,175],[163,220],[163,222],[163,278],[163,303],[164,290],[164,326],[164,333],[165,216],[165,224],[165,303],[165,311],[166,187],[166,215],[166,222],[166,313],[167,223],[167,230],[167,243],[167,258],[167,280],[168,184],[168,297],[168,328],[168,337],[169,242],[169,273],[169,309],[170,175],[170,229],[170,253],[170,355],[171,190],[171,234],[171,324],[171,341],[172,200],[172,281],[172,290],[172,303],[172,331],[172,340],[173,188],[173,205],[173,343],[173,352],[174,184],[174,186],[174,296],[174,331],[175,216],[175,289],[176,181],[176,207],[176,258],[177,325],[177,345],[178,287],[178,307],[178,328],[179,237],[179,238],[179,347],[180,232],[180,257],[181,209],[181,227],[181,301],[181,315],[182,188],[182,193],[182,344],[183,317],[183,320],[183,328],[184,215],[184,234],[184,260],[184,354],[185,200],[185,342],[185,343],[186,192],[186,196],[186,296],[187,247],[187,292],[187,311],[188,233],[188,258],[188,319],[189,214],[189,311],[189,314],[190,241],[190,267],[190,302],[190,345],[191,247],[191,248],[191,265],[191,294],[191,327],[192,249],[192,279],[192,285],[192,299],[193,254],[193,353],[194,219],[194,245],[194,249],[194,253],[194,319],[194,350],[195,246],[195,292],[196,235],[196,299],[196,346],[197,251],[197,259],[197,273],[198,272],[198,282],[198,332],[198,349],[199,252],[199,337],[200,225],[200,304],[200,327],[201,262],[201,301],[201,348],[201,356],[202,252],[202,278],[203,206],[203,225],[203,342],[204,264],[204,288],[205,265],[205,287],[206,217],[206,275],[206,339],[206,345],[207,264],[207,269],[208,223],[208,244],[208,258],[208,304],[208,356],[209,229],[209,337],[210,214],[210,329],[211,284],[211,334],[211,337],[211,356],[212,237],[212,281],[212,305],[213,270],[213,308],[214,282],[214,308],[215,233],[215,240],[215,245],[215,262],[216,249],[216,256],[216,331],[217,283],[218,241],[218,294],[219,269],[219,317],[220,250],[220,295],[221,308],[221,328],[221,347],[222,243],[222,286],[223,267],[224,267],[224,288],[225,306],[225,341],[226,302],[227,231],[227,250],[227,333],[227,352],[228,238],[228,272],[228,334],[230,290],[230,310],[230,325],[231,267],[231,343],[232,312],[233,332],[234,243],[234,266],[234,270],[235,236],[235,264],[235,311],[235,357],[236,336],[236,338],[237,291],[238,295],[238,335],[240,342],[242,328],[243,254],[243,323],[243,332],[244,259],[244,272],[244,281],[245,323],[245,330],[246,290],[247,355],[248,335],[249,274],[249,324],[250,321],[251,279],[251,286],[251,300],[252,273],[252,274],[253,311],[253,351],[254,256],[255,257],[255,269],[255,296],[257,288],[257,332],[258,289],[260,307],[260,326],[260,335],[261,277],[261,312],[261,331],[262,286],[262,307],[262,353],[263,268],[263,285],[263,297],[263,302],[264,277],[264,292],[265,275],[265,335],[266,303],[266,350],[266,352],[266,354],[268,298],[270,291],[270,310],[271,298],[271,310],[272,320],[274,338],[274,354],[276,279],[276,295],[276,304],[276,309],[277,302],[278,324],[279,284],[280,289],[280,348],[281,325],[282,313],[283,318],[283,336],[285,324],[285,327],[286,357],[287,349],[287,351],[288,317],[288,338],[290,316],[290,341],[291,340],[293,314],[293,339],[293,351],[294,339],[294,353],[295,347],[296,307],[299,343],[300,346],[301,326],[303,351],[304,332],[305,306],[307,329],[307,337],[308,345],[310,340],[312,313],[312,337],[314,315],[319,343],[321,339],[322,352],[323,327],[323,355],[329,344],[330,333],[330,346],[330,350],[338,356],[339,351],[342,347],[344,346],[344,356],[350,353]],"spineType":"ring","spineOrder":[0,1,2,3,4,5,6,7,8,9,10,11,12,13,14,15,16,17],"hist":[[0,18],[1,92],[2,188],[3,60]],"pos":[[149,0],[140,51],[114.1,95.8],[74.5,129],[25.9,146.7],[-25.9,146.7],[-74.5,129],[-114.1,95.8],[-140,51],[-149,0],[-140,-51],[-114.1,-95.8],[-74.5,-129],[-25.9,-146.7],[25.9,-146.7],[74.5,-129],[114.1,-95.8],[140,-51],[236.7,-113.7],[-247.5,-39.1],[279.1,-139.9],[-183.1,61.2],[-188.2,37.8],[41.5,-189.5],[145.3,207.4],[-94.9,-170.3],[212.4,-146.9],[187.1,91],[220.3,-124.8],[156.6,-109.4],[324.2,14.3],[171.4,-84.8],[19.3,206.9],[-18.7,250.3],[305.7,-94.4],[101.7,231.9],[-306.8,-48.2],[209.1,-142.7],[186.9,-64.1],[76,254],[162.6,191.7],[-8.6,253.1],[174,115.3],[-155.1,112.1],[305.1,-67.9],[237.7,-86.7],[151,-203.6],[220.6,124],[98.7,173.9],[217.5,222.5],[103.7,-163.9],[-54.5,187.1],[197.5,-32.3],[306.3,-76.4],[106.4,244.9],[-75.9,241.6],[-123.2,219.7],[249.3,36.3],[190,-40.8],[251,7.6],[-251,26],[243.7,61.3],[-160,195.9],[-6.6,195.8],[251,2.8],[-55,247.7],[144.3,152.7],[246.8,-70],[-23.8,261.4],[206.7,21.7],[-139.6,220.9],[-33.4,255.4],[-221.1,-118],[312.7,23.3],[193.1,45.2],[246.3,-52],[-191.2,247.5],[239.3,77.2],[281,-134.4],[256.6,-47.8],[218.1,-223.8],[-48,247.5],[3.8,-251.6],[245.3,-63.3],[175.4,256.9],[142,-211.7],[-225.1,-113.2],[151.7,123.8],[170,-187.2],[-250.3,-26.4],[185.4,175.8],[120.4,219],[252.5,111.9],[71.8,185.6],[-175.5,-91.2],[31.6,-249.2],[183.6,65],[118.4,235.7],[126.1,163.1],[-72.2,-245.8],[38.9,195.4],[262.9,-31.3],[-175.8,99.8],[292.8,115.1],[-82.8,237.9],[308.4,62.6],[115.1,227.8],[184.4,73.9],[-223.9,214.8],[-192.6,-14.1],[151.1,127.9],[-188.2,-37.4],[233.2,135.2],[132.8,144.4],[210.4,-2.8],[169.4,186.5],[79.3,192.4],[259.5,57],[-189.4,168.9],[-101.9,230.9],[276.2,-15.5],[249.9,-25.7],[225.6,111.6],[192.2,-16],[-239.7,-77],[310.3,29.9],[255.9,21.5],[252.2,-186.2],[238.9,200.4],[119.8,-152.9],[38.8,308.7],[-233.6,92.3],[10.8,250.2],[202.3,149.2],[190.9,161.1],[274.1,160.6],[309.9,-41.2],[249.6,46.3],[226.3,161.1],[247.4,188.1],[-155,199.6],[-140.2,-130.5],[-111.3,-224.3],[-70.9,240.6],[154.6,-125],[47.8,266.1],[202.2,169.6],[312.1,-28.3],[-188.3,-167.3],[307.6,49.6],[50.2,-247],[-64.6,-179.6],[-191.6,10.9],[-143.2,206.3],[-199.5,4],[74.9,241.7],[285.4,127.4],[156.2,-115.2],[315.3,63.4],[133.5,-215.5],[309,42.4],[-165.2,-108.8],[-162.3,-190.9],[-249,-43.3],[281.8,138.9],[-104.4,163.7],[-310.5,-13.4],[-152,206.3],[-68.8,304.7],[-178,177.4],[-216.9,-124.2],[59.8,266.9],[272.3,16.1],[-217.2,133.8],[137,-141.6],[267.7,158.2],[16.4,250.3],[-182.5,-58.5],[305,18.9],[42.8,247.7],[308,54.3],[-213.1,139.4],[208.1,143.6],[301.7,106.4],[124.7,-217.3],[184.3,95.6],[223.1,-117.7],[307.7,-50.7],[-194.8,47],[230.3,-102.3],[-123.5,149.8],[-10,-192.8],[84.2,235.3],[158.9,110.5],[251.7,-12.5],[247.9,41.5],[150.9,202.5],[-100.4,-230.5],[263.8,7.2],[181.1,254.2],[248.2,105.6],[250.7,-18.9],[31,250.7],[235.7,97.4],[-30.4,193.4],[13.5,312.4],[237.7,220.1],[-40.3,-186.9],[175,196.2],[131,215.9],[-125.3,-216.8],[-108.6,228],[-179.7,-69.9],[-112,-155.4],[-236.7,-100.9],[105.1,293.2],[216.5,138.9],[109.9,254.7],[-118,221],[196,2.2],[-195.3,-20.6],[242,70],[-251.9,-10.3],[-68.9,182.9],[-78.6,259.7],[18.4,-190.4],[-132.6,-136.6],[-26.8,-249.6],[274.8,53.5],[-166.5,-94.2],[298.5,90.1],[213.9,-135],[-65,243.8],[-242.1,64.9],[59.9,305.6],[-186.2,-45.9],[-227.3,105.5],[-201.2,-152.9],[193.8,183.5],[-57.9,304.7],[257,182.5],[-32.4,204],[245.6,57.2],[-222.7,116.4],[267.7,81.4],[95.3,233.6],[-246.4,44],[261.8,25.9],[28,191.8],[303.5,-84.9],[-22.7,-189.7],[-245.4,57],[-37.3,-247.5],[302.8,75.8],[-138.9,132.6],[277,-147.7],[234.6,-103.6],[303.2,82.3],[-252.6,4.5],[296.2,95.4],[140.8,208.9],[13.8,200.2],[61.2,246.9],[70.2,278.6],[0.6,-191.4],[97,251],[121.7,286.1],[167.2,-93.6],[210.1,137.5],[273.2,32.9],[-193.2,-160.5],[-149.5,124.3],[206.8,27.2],[-81.5,-175.5],[202.5,153.4],[254.7,200.7],[-220.3,125.7],[65.7,242.9],[-10.6,310.5],[-175.2,185.6],[-244.8,-50.9],[241.8,96],[-152.5,-117.9],[-168.6,186.7],[-88.2,172.4],[65.5,198.4],[150.6,272.5],[-239.4,88.9],[-92.1,235],[225.4,-112.4],[-87.2,237.4],[53.2,-186.5],[253.8,-35.1],[-96.6,174.3],[-19.7,-250.1],[163.6,204.4],[-154.7,-199.2],[58.5,309.1],[-115.4,160.1],[166.6,219.4],[111.6,260.5],[-104.8,-159.3],[-163.7,191.4],[-197.9,157],[228.1,214.9],[-38.2,243.9],[24.8,-249.8],[-57.8,-243.9],[-90.6,-235.9],[-132.5,143.8],[249,-4.3],[244.7,66.1],[-60.2,244.8],[-151.7,-202.8],[178.6,-72],[-162.2,106.7],[-57.9,201.8],[244.3,88.9],[-77.7,193.7],[-175,80.6],[231.4,110.7],[219.1,129.5],[314.7,5.7],[250.3,29.7],[7.8,259.3],[-240.7,-68.9],[224.7,119],[234.1,84.1],[312.1,-67.7],[-57.1,-185.8],[78.8,-177.8],[195.6,50.9],[157.7,-196.1],[178.5,-183],[243,-76.8],[101.4,168.8],[24.1,-190.3],[157.1,270.6],[312.4,15.9],[-134.7,211.8],[-0.7,254.5],[-13.5,193.6],[230.1,137.5],[179.6,177.5],[12.1,-251.4],[191.2,153.4],[-229.6,-82.4],[-5.5,-250.2],[-190.5,18.9],[235.6,-94.2],[-130.3,-230.6],[-185.7,187],[247.2,51.8],[155.9,195.7],[131.2,-238.9],[175.2,180.6],[316,-15.4],[148.9,235]],"bbox":[-310.4671433147335,-251.5504567757479,324.15146008298103,312.4360945441855]}